primality/__init__.py
primality/miller.py
primality/primality.py
primality-0.0.6.dist-info/LICENSE
primality-0.0.6.dist-info/METADATA
primality-0.0.6.dist-info/WHEEL
primality-0.0.6.dist-info/top_level.txt
primality-0.0.6.dist-info/RECORD
