Metadata-Version: 2.1
Name: primality
Version: 0.0.6
Summary: Primality helps you easily find, test and work with prime numbers in Python.
Home-page: UNKNOWN
License: UNKNOWN
Platform: UNKNOWN
Classifier: Programming Language :: Python :: 3
Classifier: License :: OSI Approved :: MIT License
Classifier: Operating System :: OS Independent
Requires-Python: >=3.8
